nextpoints_sdk/__init__.py
nextpoints_sdk/exceptions.py
nextpoints_sdk/py.typed
nextpoints_sdk/version.py
nextpoints_sdk/client/http_client.py
nextpoints_sdk/client/minio_client.py
nextpoints_sdk/client/services.py
nextpoints_sdk/models/annotation.py
nextpoints_sdk/models/artifacts.py
nextpoints_sdk/models/calibration.py
nextpoints_sdk/models/enums.py
nextpoints_sdk/models/errors.py
nextpoints_sdk/models/minio.py
nextpoints_sdk/models/pose.py
nextpoints_sdk/models/project.py
nextpoints_sdk/models/project_metadata.py
nextpoints_sdk/models/requests.py
nextpoints_sdk/models/responses.py
nextpoints_sdk/utils/__init__.py
nextpoints_sdk/utils/timing.py
nextpoints_sdk-0.2.0.dist-info/METADATA
nextpoints_sdk-0.2.0.dist-info/WHEEL
nextpoints_sdk-0.2.0.dist-info/top_level.txt
nextpoints_sdk-0.2.0.dist-info/RECORD
